odoo/addons/stock_move_free_reservation_reassign/README.rst
odoo/addons/stock_move_free_reservation_reassign/__init__.py
odoo/addons/stock_move_free_reservation_reassign/__manifest__.py
odoo/addons/stock_move_free_reservation_reassign/i18n/es.po
odoo/addons/stock_move_free_reservation_reassign/i18n/it.po
odoo/addons/stock_move_free_reservation_reassign/i18n/stock_move_free_reservation_reassign.pot
odoo/addons/stock_move_free_reservation_reassign/models/__init__.py
odoo/addons/stock_move_free_reservation_reassign/models/res_config_settings.py
odoo/addons/stock_move_free_reservation_reassign/models/stock_move_line.py
odoo/addons/stock_move_free_reservation_reassign/models/stock_quant.py
odoo/addons/stock_move_free_reservation_reassign/readme/CONTRIBUTORS.rst
odoo/addons/stock_move_free_reservation_reassign/readme/DESCRIPTION.rst
odoo/addons/stock_move_free_reservation_reassign/readme/USAGE.rst
odoo/addons/stock_move_free_reservation_reassign/static/description/icon.png
odoo/addons/stock_move_free_reservation_reassign/static/description/index.html
odoo/addons/stock_move_free_reservation_reassign/tests/__init__.py
odoo/addons/stock_move_free_reservation_reassign/tests/test_stock_move_free_reservation_reassign.py
odoo/addons/stock_move_free_reservation_reassign/views/res_config_settings.xml
odoo_addon_stock_move_free_reservation_reassign-16.0.1.0.1.4.dist-info/METADATA
odoo_addon_stock_move_free_reservation_reassign-16.0.1.0.1.4.dist-info/WHEEL
odoo_addon_stock_move_free_reservation_reassign-16.0.1.0.1.4.dist-info/top_level.txt
odoo_addon_stock_move_free_reservation_reassign-16.0.1.0.1.4.dist-info/RECORD
